zenv/__init__.py
zenv/__main__.py
zenv/builder.py
zenv/cli.py
zenv/runtime.py
zenv/transpiler.py
zenv/hub/__init__.py
zenv/hub/auth.py
zenv/hub/client.py
zenv/utils/__init__.py
zenv/utils/config.py
zenv/utils/hub_client.py
zenv/utils/logger.py
zenv/utils/package_manager.py
zenv_lang-2.1.0.dist-info/METADATA
zenv_lang-2.1.0.dist-info/WHEEL
zenv_lang-2.1.0.dist-info/entry_points.txt
zenv_lang-2.1.0.dist-info/top_level.txt
zenv_lang-2.1.0.dist-info/RECORD
