Metadata-Version: 2.4
Name: zenv-lang
Version: 2.1.0
Summary: Zenv Programming Language - Modern transpiler to Python
Author-email: "gopu.inc" <ceoseshell@gmail.com>
Maintainer-email: Mauricio <ceoseshell@gmail.com>
License: MIT
Project-URL: Homepage, https://zenv-hub.vercel.app
Project-URL: Documentation, https://zenv-hub.vercel.app/#
Project-URL: Repository, https://github.com/gopu-inc/zenv
Project-URL: Issues, https://github.com/gopu-inc/zenv/issues
Project-URL: Changelog, https://github.com/gopu-inc/zenv/releases
Project-URL: Discord, https://discord.gg/qWx5DszrC
Project-URL: Sponsor, https://github.com/sponsors/gopu-inc
Keywords: zenv,programming-language,transpiler,python
Classifier: Development Status :: 4 - Beta
Classifier: Intended Audience :: Developers
Classifier: Topic :: Software Development :: Build Tools
Classifier: License :: OSI Approved :: MIT License
Classifier: Programming Language :: Python :: 3
Classifier: Programming Language :: Python :: 3.7
Classifier: Programming Language :: Python :: 3.8
Classifier: Programming Language :: Python :: 3.9
Classifier: Programming Language :: Python :: 3.10
Classifier: Programming Language :: Python :: 3.11
Classifier: Programming Language :: Python :: 3.12
Classifier: Operating System :: OS Independent
Classifier: Typing :: Typed
Requires-Python: >=3.7
Requires-Dist: requests>=2.31.0
Provides-Extra: dev
Requires-Dist: pytest>=7.4.0; extra == "dev"
Requires-Dist: pytest-cov>=4.1.0; extra == "dev"
Requires-Dist: black>=23.7.0; extra == "dev"
Requires-Dist: flake8>=6.0.0; extra == "dev"
Requires-Dist: mypy>=1.5.0; extra == "dev"
Requires-Dist: isort>=5.12.0; extra == "dev"
Requires-Dist: twine>=4.0.2; extra == "dev"
Requires-Dist: build>=0.10.0; extra == "dev"
Requires-Dist: pre-commit>=3.4.0; extra == "dev"
Provides-Extra: docs
Requires-Dist: mkdocs>=1.5.0; extra == "docs"
Requires-Dist: mkdocs-material>=9.2.0; extra == "docs"
Requires-Dist: mkdocstrings[python]>=0.22.0; extra == "docs"
Requires-Dist: mkdocs-redirects>=1.2.0; extra == "docs"
Provides-Extra: test
Requires-Dist: pytest>=7.4.0; extra == "test"
Requires-Dist: pytest-cov>=4.1.0; extra == "test"
Requires-Dist: pytest-mock>=3.11.0; extra == "test"
Requires-Dist: pytest-asyncio>=0.21.0; extra == "test"
Provides-Extra: all
Requires-Dist: zenv-lang[dev]; extra == "all"
Requires-Dist: zenv-lang[docs]; extra == "all"
Requires-Dist: zenv-lang[test]; extra == "all"
